pysnmp/__init__.py
pysnmp/cache.py
pysnmp/carrier/__init__.py
pysnmp/carrier/asyncio/__init__.py
pysnmp/carrier/asyncio/base.py
pysnmp/carrier/asyncio/dgram/__init__.py
pysnmp/carrier/asyncio/dgram/base.py
pysnmp/carrier/asyncio/dgram/udp.py
pysnmp/carrier/asyncio/dgram/udp6.py
pysnmp/carrier/asyncio/dgram/unix.py
pysnmp/carrier/asyncio/dispatch.py
pysnmp/carrier/base.py
pysnmp/carrier/error.py
pysnmp/carrier/sockfix.py
pysnmp/carrier/sockmsg.py
pysnmp/debug.py
pysnmp/entity/__init__.py
pysnmp/entity/config.py
pysnmp/entity/engine.py
pysnmp/entity/observer.py
pysnmp/entity/rfc3413/__init__.py
pysnmp/entity/rfc3413/cmdgen.py
pysnmp/entity/rfc3413/cmdrsp.py
pysnmp/entity/rfc3413/config.py
pysnmp/entity/rfc3413/context.py
pysnmp/entity/rfc3413/mibvar.py
pysnmp/entity/rfc3413/ntforg.py
pysnmp/entity/rfc3413/ntfrcv.py
pysnmp/entity/rfc3413/oneliner/__init__.py
pysnmp/entity/rfc3413/oneliner/cmdgen.py
pysnmp/entity/rfc3413/oneliner/ntforg.py
pysnmp/error.py
pysnmp/hlapi/asyncio/__init__.py
pysnmp/hlapi/asyncio/auth.py
pysnmp/hlapi/asyncio/cmdgen.py
pysnmp/hlapi/asyncio/context.py
pysnmp/hlapi/asyncio/lcd.py
pysnmp/hlapi/asyncio/ntforg.py
pysnmp/hlapi/asyncio/slim.py
pysnmp/hlapi/asyncio/transport.py
pysnmp/hlapi/asyncio/varbinds.py
pysnmp/hlapi/transport.py
pysnmp/nextid.py
pysnmp/proto/__init__.py
pysnmp/proto/acmod/__init__.py
pysnmp/proto/acmod/rfc3415.py
pysnmp/proto/acmod/void.py
pysnmp/proto/api/__init__.py
pysnmp/proto/api/v1.py
pysnmp/proto/api/v2c.py
pysnmp/proto/api/verdec.py
pysnmp/proto/cache.py
pysnmp/proto/errind.py
pysnmp/proto/error.py
pysnmp/proto/mpmod/__init__.py
pysnmp/proto/mpmod/base.py
pysnmp/proto/mpmod/cache.py
pysnmp/proto/mpmod/rfc2576.py
pysnmp/proto/mpmod/rfc3412.py
pysnmp/proto/proxy/__init__.py
pysnmp/proto/proxy/rfc2576.py
pysnmp/proto/rfc1155.py
pysnmp/proto/rfc1157.py
pysnmp/proto/rfc1901.py
pysnmp/proto/rfc1902.py
pysnmp/proto/rfc1905.py
pysnmp/proto/rfc3411.py
pysnmp/proto/rfc3412.py
pysnmp/proto/secmod/__init__.py
pysnmp_lextudio-6.2.1.dist-info/LICENSE.rst
pysnmp_lextudio-6.2.1.dist-info/METADATA
pysnmp_lextudio-6.2.1.dist-info/WHEEL
pysnmp_lextudio-6.2.1.dist-info/RECORD
