Metadata-Version: 2.1
Name: pysnmp-lextudio
Version: 6.2.1
Summary: A Python library for SNMP
Home-page: https://github.com/lextudio/pysnmp
License: BSD-2-Clause
Author: Ilya Etingof
Author-email: etingof@gmail.com
Requires-Python: >=3.8,<4.0
Classifier: Development Status :: 5 - Production/Stable
Classifier: Environment :: Console
Classifier: Intended Audience :: Developers
Classifier: Intended Audience :: Information Technology
Classifier: Intended Audience :: System Administrators
Classifier: Intended Audience :: Telecommunications Industry
Classifier: License :: OSI Approved :: BSD License
Classifier: Natural Language :: English
Classifier: Operating System :: OS Independent
Classifier: Programming Language :: Python :: 3
Classifier: Programming Language :: Python :: 3.8
Classifier: Programming Language :: Python :: 3.9
Classifier: Programming Language :: Python :: 3.10
Classifier: Programming Language :: Python :: 3.11
Classifier: Programming Language :: Python :: 3.12
Classifier: Topic :: Communications
Classifier: Topic :: Software Development :: Libraries :: Python Modules
Requires-Dist: pyasn1 (>=0.4.8,!=0.5.0)
Requires-Dist: pysmi-lextudio (>=1.3.0,<2.0.0)
Requires-Dist: pysnmpcrypto (>=0.0.4,<0.0.5)
Requires-Dist: pytest-cov (>=4.0.0,<5.0.0)
Project-URL: Repository, https://github.com/lextudio/pysnmp
